pokeauth/__init__.py
pokeauth/pokeauth.py
pokeauth-0.0.1.dist-info/DESCRIPTION.rst
pokeauth-0.0.1.dist-info/METADATA
pokeauth-0.0.1.dist-info/metadata.json
pokeauth-0.0.1.dist-info/RECORD
pokeauth-0.0.1.dist-info/top_level.txt
pokeauth-0.0.1.dist-info/WHEEL
